csrd/__init__.py
csrd/controller/__init__.py
csrd/controller/controller.py
csrd/delegate/__init__.py
csrd/delegate/delegate.py
csrd/models/__init__.py
csrd/models/config.py
csrd/repository/__init__.py
csrd/repository/repository.py
csrd/router/__init__.py
csrd/router/router.py
csrd/service/__init__.py
csrd/service/service.py
csrd/utilities/__init__.py
csrd/utilities/swaggerize.py
csrd-0.1.11.dist-info/METADATA
csrd-0.1.11.dist-info/WHEEL
csrd-0.1.11.dist-info/RECORD
