Metadata-Version: 2.1
Name: csrd
Version: 0.1.11
Summary: 
Author: aaron
Author-email: aaron@frostmn.com
Requires-Python: >=3.12,<4.0
Classifier: Programming Language :: Python :: 3
Classifier: Programming Language :: Python :: 3.12
Classifier: Programming Language :: Python :: 3.13
Requires-Dist: csrd-swaggerize (>=0.1,<0.2)
Requires-Dist: flask (>=3.0.3,<4.0.0)
Requires-Dist: httpx (>=0.27.2,<0.28.0)
Requires-Dist: pydantic (>=2.8.2,<3.0.0)
